halide-21.0.0.data/data/share/cmake/Halide/HalideConfigVersion.cmake
halide-21.0.0.data/data/share/cmake/Halide/HalideConfig.cmake
halide-21.0.0.data/data/share/cmake/HalideHelpers/HalideHelpersConfigVersion.cmake
halide-21.0.0.data/data/share/cmake/HalideHelpers/HalideHelpersConfig.cmake
halide/imageio.py
halide/__init__.py
halide/halide_.cpython-312-darwin.so
halide/_generator_helpers.py
halide/bin/gengen
halide/bin/get_host_target
halide/bin/anderson2021_weightsdir_to_weightsfile
halide/bin/adams2019_weightsdir_to_weightsfile
halide/bin/anderson2021_retrain_cost_model
halide/bin/adams2019_retrain_cost_model
halide/bin/featurization_to_sample
halide/include/Halide.h
halide/include/HalidePyTorchHelpers.h
halide/include/HalideRuntimeOpenCL.h
halide/include/HalideRuntimeD3D12Compute.h
halide/include/HalideRuntimeVulkan.h
halide/include/HalideRuntimeHexagonDma.h
halide/include/HalideRuntimeCuda.h
halide/include/HalideRuntimeQurt.h
halide/include/HalideRuntime.h
halide/include/HalideBuffer.h
halide/include/HalideRuntimeMetal.h
halide/include/HalideRuntimeWebGPU.h
halide/include/HalidePyTorchCudaHelpers.h
halide/include/HalideRuntimeHexagonHost.h
halide/lib/libHalide.dylib
halide/lib/libautoschedule_mullapudi2016.so
halide/lib/libautoschedule_anderson2021.so
halide/lib/libHalide_GenGen.a
halide/lib/libautoschedule_adams2019.so
halide/lib/libHalidePyStubs.a
halide/lib/libautoschedule_li2018.so
halide/lib/cmake/Halide/HalideConfigVersion.cmake
halide/lib/cmake/Halide/FindV8.cmake
halide/lib/cmake/Halide/Halide-shared-targets.cmake
halide/lib/cmake/Halide/Halide-shared-deps.cmake
halide/lib/cmake/Halide/FindHalide_LLVM.cmake
halide/lib/cmake/Halide/Halide-shared-targets-release.cmake
halide/lib/cmake/Halide/HalideConfig.cmake
halide/lib/cmake/HalideHelpers/Halide-Interfaces-release.cmake
halide/lib/cmake/HalideHelpers/HalideTargetHelpers.cmake
halide/lib/cmake/HalideHelpers/HalideGeneratorHelpers.cmake
halide-21.0.0.dist-info/RECORD
halide-21.0.0.dist-info/WHEEL
halide-21.0.0.dist-info/METADATA
halide-21.0.0.dist-info/licenses/LICENSE.txt
