Metadata-Version: 2.2
Name: halide
Version: 21.0.0
Summary: Halide is a programming language designed to make it easier to write high-performance image and array processing code.
Keywords: array,compiler,domain-specific language,dsl,gpu,hexagon,image processing,machine learning,performance,programming language
Author-Email: The Halide team <halide-dev@lists.csail.mit.edu>
Maintainer-Email: Alex Reinking <areinking@adobe.com>
License: Copyright (c) 2012-2020 MIT CSAIL, Google, Facebook, Adobe, NVIDIA CORPORATION, and other contributors.
Classifier: Development Status :: 5 - Production/Stable
Classifier: Environment :: GPU
Classifier: Environment :: GPU :: NVIDIA CUDA
Classifier: Environment :: WebAssembly
Classifier: Intended Audience :: Developers
Classifier: Intended Audience :: Science/Research
Classifier: License :: OSI Approved :: MIT License
Classifier: Natural Language :: English
Classifier: Operating System :: MacOS
Classifier: Operating System :: Microsoft :: Windows
Classifier: Operating System :: POSIX
Classifier: Programming Language :: C++
Classifier: Programming Language :: Python :: 3
Classifier: Programming Language :: Python :: 3 :: Only
Classifier: Programming Language :: Python :: 3.9
Classifier: Programming Language :: Python :: 3.10
Classifier: Programming Language :: Python :: 3.11
Classifier: Programming Language :: Python :: 3.12
Classifier: Programming Language :: Python :: 3.13
Classifier: Programming Language :: Python :: Implementation :: CPython
Classifier: Topic :: Multimedia :: Graphics
Classifier: Topic :: Scientific/Engineering
Classifier: Topic :: Scientific/Engineering :: Artificial Intelligence
Classifier: Topic :: Scientific/Engineering :: Image Processing
Classifier: Topic :: Software Development :: Code Generators
Classifier: Topic :: Software Development :: Compilers
Classifier: Topic :: Software Development :: Libraries
Project-URL: Homepage, https://halide-lang.org
Project-URL: Documentation, https://github.com/halide/Halide/blob/main/doc/Python.md
Project-URL: Documentation (C++), https://halide-lang.org/docs
Project-URL: Issues, https://github.com/halide/Halide/issues
Project-URL: Repository, https://github.com/halide/Halide.git
Requires-Python: >=3.9
Requires-Dist: imageio>=2
Requires-Dist: numpy>=1.26
